rxiv_maker/__init__.py
rxiv_maker/__version__.py
rxiv_maker/rxiv_maker_cli.py
rxiv_maker/validate.py
rxiv_maker/cli/__init__.py
rxiv_maker/cli/__main__.py
rxiv_maker/cli/framework.py
rxiv_maker/cli/interactive.py
rxiv_maker/cli/interactive_prompts.py
rxiv_maker/cli/main.py
rxiv_maker/cli/commands/__init__.py
rxiv_maker/cli/commands/arxiv.py
rxiv_maker/cli/commands/bibliography.py
rxiv_maker/cli/commands/build.py
rxiv_maker/cli/commands/cache_management.py
rxiv_maker/cli/commands/changelog.py
rxiv_maker/cli/commands/check_installation.py
rxiv_maker/cli/commands/clean.py
rxiv_maker/cli/commands/completion.py
rxiv_maker/cli/commands/config.py
rxiv_maker/cli/commands/create_repo.py
rxiv_maker/cli/commands/docx.py
rxiv_maker/cli/commands/figures.py
rxiv_maker/cli/commands/get_rxiv_preprint.py
rxiv_maker/cli/commands/init.py
rxiv_maker/cli/commands/install_deps.py
rxiv_maker/cli/commands/repo_init.py
rxiv_maker/cli/commands/repos.py
rxiv_maker/cli/commands/repos_search.py
rxiv_maker/cli/commands/setup.py
rxiv_maker/cli/commands/track_changes.py
rxiv_maker/cli/commands/upgrade.py
rxiv_maker/cli/commands/validate.py
rxiv_maker/cli/commands/version.py
rxiv_maker/cli/framework/__init__.py
rxiv_maker/cli/framework/base.py
rxiv_maker/cli/framework/cache_commands.py
rxiv_maker/cli/framework/config_commands.py
rxiv_maker/cli/framework/content_commands.py
rxiv_maker/cli/framework/decorators.py
rxiv_maker/cli/framework/utility_commands.py
rxiv_maker/cli/framework/workflow_commands.py
rxiv_maker/config/defaults.py
rxiv_maker/config/validator.py
rxiv_maker/converters/__init__.py
rxiv_maker/converters/citation_processor.py
rxiv_maker/converters/code_processor.py
rxiv_maker/converters/comment_processor.py
rxiv_maker/converters/custom_command_processor.py
rxiv_maker/converters/figure_processor.py
rxiv_maker/converters/html_processor.py
rxiv_maker/converters/list_processor.py
rxiv_maker/converters/math_processor.py
rxiv_maker/converters/md2tex.py
rxiv_maker/converters/python_executor.py
rxiv_maker-1.18.3.dist-info/METADATA
rxiv_maker-1.18.3.dist-info/WHEEL
rxiv_maker-1.18.3.dist-info/entry_points.txt
rxiv_maker-1.18.3.dist-info/licenses/LICENSE
rxiv_maker-1.18.3.dist-info/RECORD
