Metadata-Version: 2.4
Name: rxiv-maker
Version: 1.18.3
Summary: Write scientific preprints in Markdown. Generate publication-ready PDFs efficiently.
Project-URL: Homepage, https://github.com/HenriquesLab/rxiv-maker
Project-URL: Documentation, https://github.com/HenriquesLab/rxiv-maker#readme
Project-URL: Repository, https://github.com/HenriquesLab/rxiv-maker
Project-URL: Issues, https://github.com/HenriquesLab/rxiv-maker/issues
Project-URL: Changelog, https://github.com/HenriquesLab/rxiv-maker/blob/main/CHANGELOG.md
Project-URL: Bug Reports, https://github.com/HenriquesLab/rxiv-maker/issues
Project-URL: Source Code, https://github.com/HenriquesLab/rxiv-maker
Author-email: Rxiv-Maker Contributors <rxiv.maker@gmail.com>
License-File: LICENSE
Keywords: automation,cli,command-line,hatch,latex,markdown,publishing,scientific-writing
Classifier: Development Status :: 4 - Beta
Classifier: Intended Audience :: Science/Research
Classifier: License :: OSI Approved :: MIT License
Classifier: Operating System :: OS Independent
Classifier: Programming Language :: Python :: 3
Classifier: Programming Language :: Python :: 3.10
Classifier: Programming Language :: Python :: 3.11
Classifier: Programming Language :: Python :: 3.12
Classifier: Topic :: Scientific/Engineering
Classifier: Topic :: Text Processing :: Markup :: LaTeX
Classifier: Topic :: Text Processing :: Markup :: Markdown
Requires-Python: >=3.10
Requires-Dist: click>=8.0.0
Requires-Dist: crossref-commons>=0.0.7
Requires-Dist: gitpython>=3.1.0
Requires-Dist: henriqueslab-updater>=1.2.0
Requires-Dist: latex2mathml>=3.78.0
Requires-Dist: matplotlib>=3.7.0
Requires-Dist: numpy>=1.24.0
Requires-Dist: packaging>=21.0.0
Requires-Dist: pandas>=2.0.0
Requires-Dist: pdf2image>=1.16.0
Requires-Dist: pillow>=9.0.0
Requires-Dist: platformdirs>=4.0.0
Requires-Dist: playwright>=1.54.0
Requires-Dist: prompt-toolkit>=3.0.0
Requires-Dist: pypdf>=6.0.0
Requires-Dist: python-docx>=1.1.0
Requires-Dist: python-dotenv>=1.0.0
Requires-Dist: pyyaml>=6.0.0
Requires-Dist: requests>=2.28.0
Requires-Dist: rich-click>=1.6.0
Requires-Dist: rich>=13.0.0
Requires-Dist: seaborn>=0.12.0
Requires-Dist: tomli-w>=1.0.0
Requires-Dist: typing-extensions>=4.0.0
Provides-Extra: dev
Requires-Dist: build>=1.2.2.post1; extra == 'dev'
Requires-Dist: coverage[toml]>=7.0; extra == 'dev'
Requires-Dist: hatch>=1.14.1; extra == 'dev'
Requires-Dist: mypy>=1.0; extra == 'dev'
Requires-Dist: nbstripout>=0.7.1; extra == 'dev'
Requires-Dist: nox>=2023.0.0; extra == 'dev'
Requires-Dist: pre-commit>=4.2.0; extra == 'dev'
Requires-Dist: pypdf2>=3.0.0; extra == 'dev'
Requires-Dist: pytest-asyncio>=0.21.0; extra == 'dev'
Requires-Dist: pytest-benchmark>=4.0.0; extra == 'dev'
Requires-Dist: pytest-clarity>=1.0.0; extra == 'dev'
Requires-Dist: pytest-cov>=4.0; extra == 'dev'
Requires-Dist: pytest-datadir>=1.4.0; extra == 'dev'
Requires-Dist: pytest-env>=1.0.0; extra == 'dev'
Requires-Dist: pytest-mock>=3.10.0; extra == 'dev'
Requires-Dist: pytest-notebook>=0.10.0; extra == 'dev'
Requires-Dist: pytest-snapshot>=0.9.0; extra == 'dev'
Requires-Dist: pytest-sugar>=0.9.7; extra == 'dev'
Requires-Dist: pytest-timeout>=2.0.0; extra == 'dev'
Requires-Dist: pytest-xdist>=3.8.0; extra == 'dev'
Requires-Dist: pytest<10.0,>=7.4; extra == 'dev'
Requires-Dist: ruff>=0.12.2; extra == 'dev'
Requires-Dist: twine>=6.1.0; extra == 'dev'
Requires-Dist: types-pyyaml>=6.0.0; extra == 'dev'
Requires-Dist: types-requests>=2.32.4.20250611; extra == 'dev'
